{
    "grant_title": null,
    "funding_amount": null,
    "deadline": null,
    "eligible_applicant_type": [
        "Non-profit organizations",
        "Community groups",
        "Local government entities"
    ],
    "geographic_restrictions": "Montpelier, Vermont",
    "project_area": "Brick-and-mortar projects with a 20-year lifespan",
    "demographic_requirements": null,
    "eligibility_summary": "Projects must be brick-and-mortar with a 20-year lifespan and provide long-term public benefits in Montpelier. Grants typically range from $1,000 to $5,000, rarely exceeding $10,000."
}