{
    "grant_title": "Allentown Arts & Culture Project Grants",
    "funding_amount": null,
    "deadline": "January 31, 2025",
    "eligible_applicant_type": [
        "independent artists",
        "nonprofit arts and cultural organizations"
    ],
    "geographic_restrictions": "Projects should include and impact residents of downtown Allentown. Artists and nonprofit arts and cultural organizations based in the Lehigh Valley are invited to apply.",
    "project_area": "arts and culture projects with high community impact and engagement",
    "demographic_requirements": null,
    "eligibility_summary": "Independent artists and nonprofit arts and cultural organizations based in the Lehigh Valley are eligible to apply for funding to support projects that engage and impact downtown Allentown residents."
}