{
    "grant_title": "Citywide Climate Resiliency Plan",
    "funding_amount": null,
    "deadline": "November 5th, 2:00 PM",
    "eligible_applicant_type": [
        "qualified consultant team"
    ],
    "geographic_restrictions": "All neighborhoods in Bridgeport, Connecticut",
    "project_area": "Climate resilience planning with focus on infrastructure, social, environmental, and economic resilience",
    "demographic_requirements": "Ensuring representation of all neighborhoods in Bridgeport",
    "eligibility_summary": "Open to qualified consultant teams to lead the development of a citywide Climate Resiliency Plan, including data analysis, community engagement, and plan preparation."
}